minchin/scripts/photosorter/__init__.py
minchin/scripts/photosorter/tests/__init__.py
minchin/scripts/photosorter/tests/test_sorter.py
minchin/scripts/photosorter/tests/test_examples/2004-05-07 20.16.31.jpg
minchin/scripts/photosorter/tests/test_examples/2006-09-09 07.00.24-alt.jpg
minchin/scripts/photosorter/tests/test_examples/2006-09-09 07.00.24.jpg
minchin/scripts/photosorter/tests/test_examples/2014-02-06 09.15.17.jpg
minchin/scripts/photosorter/tests/test_examples/no-exif.jpg
minchin/scripts/photosorter/tests/test_examples/test.png
minchin/scripts/photosorter/tests/test_examples/root/2006/2006-09/2006-09-09 07.00.24-1.jpg
minchin/scripts/photosorter/tests/test_examples/root/2006/2006-09/2006-09-09 07.00.24.jpg
minchin_scripts_photosorter-2.2.0.dist-info/licenses/LICENSE.txt
minchin_scripts_photosorter-2.2.0.dist-info/METADATA
minchin_scripts_photosorter-2.2.0.dist-info/WHEEL
minchin_scripts_photosorter-2.2.0.dist-info/entry_points.txt
minchin_scripts_photosorter-2.2.0.dist-info/top_level.txt
minchin_scripts_photosorter-2.2.0.dist-info/RECORD
