Metadata-Version: 2.4
Name: minchin.scripts.photosorter
Version: 2.2.0
Summary: A Python script to keep my photos from Dropbox organized.
Author-email: William Minchin <w_minchin@hotmail.com>
Maintainer-email: William Minchin <w_minchin@hotmail.com>
License-Expression: MIT
Project-URL: Bug Tracker, https://github.com/MinchinWeb/minchin.scripts.photosorter/issues
Project-URL: Repository, https://github.com/MinchinWeb/minchin.scripts.photosorter
Classifier: Development Status :: 4 - Beta
Classifier: Environment :: Console
Classifier: Programming Language :: Python :: 3
Classifier: Programming Language :: Python :: 3.6
Classifier: Natural Language :: English
Classifier: Intended Audience :: Developers
Classifier: Operating System :: OS Independent
Classifier: Topic :: Software Development :: Libraries :: Python Modules
License-File: LICENSE.txt
Requires-Dist: argcomplete>=1.3.0
Requires-Dist: ExifRead>=2.1.2
Requires-Dist: watchdog>=0.8.3
Provides-Extra: dev
Requires-Dist: coveralls>=1.1; extra == "dev"
Requires-Dist: pytest-xdist>=1.14; extra == "dev"
Requires-Dist: pytest>=2.9.2; extra == "dev"
Requires-Dist: mypy; extra == "dev"
Requires-Dist: pip-tools>=6; extra == "dev"
Requires-Dist: minchin.releaser>=0.9.6; extra == "dev"
Requires-Dist: minchin.text; extra == "dev"
Requires-Dist: urllib3>=1.26.5; extra == "dev"
Requires-Dist: pytest>=7.2.0; extra == "dev"
Requires-Dist: Pygments>=2.15.0; extra == "dev"
Requires-Dist: bleach>=3.3.0; extra == "dev"
Requires-Dist: requests>=2.31.0; extra == "dev"
Dynamic: license-file
